sqlite3utils/__init__.py
sqlite3utils/main.py
sqlite3utils-0.5.dist-info/METADATA
sqlite3utils-0.5.dist-info/WHEEL
sqlite3utils-0.5.dist-info/top_level.txt
sqlite3utils-0.5.dist-info/RECORD
