Metadata-Version: 2.1
Name: sqlite3utils
Version: 0.5
Summary: UNKNOWN
Home-page: https://github.com/technicalheist/sqlite3utils.git
Author: Technical Heist
Author-email: contact@technicalheist.com
License: MIT
Keywords: SQLite,database,CRUD,utility
Platform: UNKNOWN
Classifier: Development Status :: 3 - Alpha
Classifier: Intended Audience :: Developers
Classifier: License :: OSI Approved :: MIT License
Classifier: Programming Language :: Python :: 3
Classifier: Programming Language :: Python :: 3.6
Classifier: Programming Language :: Python :: 3.7
Classifier: Programming Language :: Python :: 3.8
Classifier: Programming Language :: Python :: 3.9
